odoo8_addon_timesheet_task-8.0.0.2.1-py2.7-nspkg.pth
odoo8_addon_timesheet_task-8.0.0.2.1.dist-info/top_level.txt
odoo8_addon_timesheet_task-8.0.0.2.1.dist-info/WHEEL
odoo8_addon_timesheet_task-8.0.0.2.1.dist-info/RECORD
odoo8_addon_timesheet_task-8.0.0.2.1.dist-info/metadata.json
odoo8_addon_timesheet_task-8.0.0.2.1.dist-info/DESCRIPTION.rst
odoo8_addon_timesheet_task-8.0.0.2.1.dist-info/METADATA
odoo8_addon_timesheet_task-8.0.0.2.1.dist-info/namespace_packages.txt
odoo_addons/timesheet_task/__openerp__.py
odoo_addons/timesheet_task/project_task.py
odoo_addons/timesheet_task/project_task_view.xml
odoo_addons/timesheet_task/__init__.py
odoo_addons/timesheet_task/report/hr_timesheet_report.py
odoo_addons/timesheet_task/report/hr_timesheet_report_view.xml
odoo_addons/timesheet_task/report/__init__.py
odoo_addons/timesheet_task/i18n/fr.po
odoo_addons/timesheet_task/test/task_timesheet_indicators.yml
odoo_addons/timesheet_task/static/description/icon.png
